iqsms_rest/__init__.py
iqsms_rest/gate.py
iqsms_rest-0.0.4.dist-info/LICENSE
iqsms_rest-0.0.4.dist-info/METADATA
iqsms_rest-0.0.4.dist-info/WHEEL
iqsms_rest-0.0.4.dist-info/top_level.txt
iqsms_rest-0.0.4.dist-info/RECORD
