Metadata-Version: 2.1
Name: iqsms-rest
Version: 0.0.4
Summary: Модуль для работы с REST API смс-шлюза iqsms.ru (СМС Дисконт)
Home-page: UNKNOWN
Author: Chmelyuk Vladislav
Author-email: neimp@yandex.ru
License: UNKNOWN
Platform: UNKNOWN
Classifier: License :: Public Domain
Classifier: Natural Language :: Russian
Classifier: Operating System :: OS Independent
Classifier: Programming Language :: Python
Classifier: Programming Language :: Python :: 3
Classifier: Programming Language :: Python :: 3 :: Only
Classifier: Programming Language :: Python :: 3.6
Classifier: Programming Language :: Python :: 3.7
Classifier: Programming Language :: Python :: 3.8
Classifier: Programming Language :: Python :: 3.9
Classifier: Programming Language :: Python :: 3.10
Classifier: Topic :: Communications
Classifier: Topic :: Utilities
Requires-Dist: requests
